messy_xlsx/__init__.py
messy_xlsx/cache.py
messy_xlsx/exceptions.py
messy_xlsx/models.py
messy_xlsx/multi_sheet.py
messy_xlsx/sheet.py
messy_xlsx/utils.py
messy_xlsx/workbook.py
messy_xlsx/detection/__init__.py
messy_xlsx/detection/format_detector.py
messy_xlsx/detection/locale_detector.py
messy_xlsx/detection/structure_analyzer.py
messy_xlsx/formulas/__init__.py
messy_xlsx/formulas/config.py
messy_xlsx/formulas/engine.py
messy_xlsx/normalization/__init__.py
messy_xlsx/normalization/dates.py
messy_xlsx/normalization/missing_values.py
messy_xlsx/normalization/numbers.py
messy_xlsx/normalization/pipeline.py
messy_xlsx/normalization/type_coercion.py
messy_xlsx/normalization/type_inference.py
messy_xlsx/normalization/whitespace.py
messy_xlsx/parsing/__init__.py
messy_xlsx/parsing/base_handler.py
messy_xlsx/parsing/csv_handler.py
messy_xlsx/parsing/handler_registry.py
messy_xlsx/parsing/xls_handler.py
messy_xlsx/parsing/xlsx_handler.py
messy_xlsx-0.7.2.dist-info/METADATA
messy_xlsx-0.7.2.dist-info/WHEEL
messy_xlsx-0.7.2.dist-info/licenses/LICENSE
messy_xlsx-0.7.2.dist-info/RECORD
