Metadata-Version: 2.4
Name: messy-xlsx
Version: 0.7.2
Summary: A Python library for parsing messy Excel files with intelligent structure detection and formula evaluation
Project-URL: Homepage, https://github.com/ivan-loh/messy-xlsx
Project-URL: Repository, https://github.com/ivan-loh/messy-xlsx
Project-URL: Issues, https://github.com/ivan-loh/messy-xlsx/issues
Author: Ivan
License-Expression: MIT
License-File: LICENSE
Keywords: data-extraction,excel,pandas,parser,spreadsheet,xlsx
Classifier: Development Status :: 3 - Alpha
Classifier: Intended Audience :: Developers
Classifier: License :: OSI Approved :: MIT License
Classifier: Programming Language :: Python :: 3
Classifier: Programming Language :: Python :: 3.10
Classifier: Programming Language :: Python :: 3.11
Classifier: Programming Language :: Python :: 3.12
Classifier: Topic :: Office/Business :: Financial :: Spreadsheet
Classifier: Topic :: Software Development :: Libraries :: Python Modules
Requires-Python: >=3.10
Requires-Dist: fastexcel>=0.11.0
Requires-Dist: numpy>=1.24.0
Requires-Dist: openpyxl>=3.1.0
Requires-Dist: pandas>=2.0.0
Provides-Extra: all
Requires-Dist: formulas>=1.2.0; extra == 'all'
Requires-Dist: xlcalculator>=0.4.0; extra == 'all'
Requires-Dist: xlrd>=2.0.0; extra == 'all'
Provides-Extra: dev
Requires-Dist: hypothesis>=6.0; extra == 'dev'
Requires-Dist: mypy>=1.0; extra == 'dev'
Requires-Dist: pyarrow>=14.0; extra == 'dev'
Requires-Dist: pytest-cov>=4.0; extra == 'dev'
Requires-Dist: pytest>=7.0; extra == 'dev'
Requires-Dist: ruff>=0.1.0; extra == 'dev'
Provides-Extra: formulas
Requires-Dist: formulas>=1.2.0; extra == 'formulas'
Requires-Dist: xlcalculator>=0.4.0; extra == 'formulas'
Provides-Extra: xls
Requires-Dist: xlrd>=2.0.0; extra == 'xls'
